[
    {
    "name": "WON COin",
    "address": "0xbe68b4645ab798ed4db88192a444898ff4fda5ae",
    "symbol": "WON",
    "decimals": 8,
    "logo": "https://github.saturn.network/eth/logo/WONCoin.png",
    "website": "https://wonproject.co/",
    "twitter": "https://twitter.com/wonprojectPH",
    "telegram": "https://t.me/joinchat/Pu7mGRbwbLBmvmOgKpkEzw",
    "facebook": "https://www.facebook.com/wonprojectofficial/",
    "medium": "https://medium.com/@woncoinproject",
    "github": "https://github.com/WONProject",
  }
  ]
